simple_calculator_pws/__init__.py
simple_calculator_pws/operations.py
simple_calculator_pws-0.0.1.dist-info/METADATA
simple_calculator_pws-0.0.1.dist-info/WHEEL
simple_calculator_pws-0.0.1.dist-info/top_level.txt
simple_calculator_pws-0.0.1.dist-info/RECORD
