Metadata-Version: 2.1
Name: simple-calculator-pws
Version: 0.0.1
Summary: Calculadora básica para demonstração de criação de pacote
Home-page: https://github.com/PauloWilly/DIO_Projetos/Criacao_Pacotes_Python
Author: Paulo William
Author-email: ziunewill@gmail.com
License: UNKNOWN
Platform: UNKNOWN
Requires-Python: >=3.7
